{
  "questions": [
    {
      "id": 1,
      "question": "What is the capital of France?",
      "type": "single",
      "options": ["Paris", "London", "Berlin", "Madrid"],
      "correctAnswer": "Paris",
      "weight": 2
    },
    {
      "id": 2,
      "question": "Select all prime numbers:",
      "type": "multiple",
      "options": ["2", "3", "4", "5"],
      "correctAnswer": ["2", "3", "5"],
      "weight": 3
    },
    {
      "id": 3,
      "question": "Which language is primarily used for web development?",
      "type": "single",
      "options": ["Python", "JavaScript", "C++", "Java"],
      "correctAnswer": "JavaScript",
      "weight": 2
    },
    {
      "id": 4,
      "question": "Select all colors that are part of the RGB model:",
      "type": "multiple",
      "options": ["Red", "Green", "Blue", "Yellow"],
      "correctAnswer": ["Red", "Green", "Blue"],
      "weight": 3
    },
    {
      "id": 5,
      "question": "Which planet is known as the Red Planet?",
      "type": "single",
      "options": ["Earth", "Mars", "Jupiter", "Venus"],
      "correctAnswer": "Mars",
      "weight": 2
    }
  ]
}